jardecompiler/__init__.py
jardecompiler/__main__.py
jardecompiler/decompile.py
jardecompiler-0.2.0.dist-info/licenses/LICENSE
jardecompiler-0.2.0.dist-info/METADATA
jardecompiler-0.2.0.dist-info/WHEEL
jardecompiler-0.2.0.dist-info/entry_points.txt
jardecompiler-0.2.0.dist-info/top_level.txt
jardecompiler-0.2.0.dist-info/RECORD
