Metadata-Version: 2.4
Name: jardecompiler
Version: 0.2.0
Summary: A Python-native tool to unzip and decompile JAR files also huge thanks to who made CRF for the decompilation logic this requires java to be installed
Author: Casey
License: MIT
Requires-Python: >=3.7
License-File: LICENSE
Dynamic: license-file
